{"date": "2026-07-20", "sectors": [{"sector": "Health Care", "count": 168, "rs_now_avg": 58, "rs_line_avg": 55, "rs_line_bayes": 55, "sector_health": 0.04, "phase_counts": {"newEntry": 4, "recentUp": 59, "progressing": 11, "stagnant": 50, "transDn": 44, "p4Plus": 4, "total": 168}, "industries": [{"industry": "Health Care Services", "rs_line_avg": 61, "count": 22, "top_tickers": [{"ticker": "BTSG", "rs": 98, "pattern": "Cup"}, {"ticker": "NEO", "rs": 98, "pattern": "HT Flag"}, {"ticker": "LFST", "rs": 97, "pattern": "HT Flag"}, {"ticker": "VCYT", "rs": 97, "pattern": "HT Flag"}, {"ticker": "AMN", "rs": 95, "pattern": "HT Flag"}, {"ticker": "DVA", "rs": 94, "pattern": "HT Flag"}]}, {"industry": "Health Care Supplies", "rs_line_avg": 59, "count": 13, "top_tickers": [{"ticker": "AVNS", "rs": 93, "pattern": "Flat Base"}, {"ticker": "NEOG", "rs": 90, "pattern": "Cup"}, {"ticker": "WST", "rs": 88, "pattern": "VCP"}, {"ticker": "LNTH", "rs": 85, "pattern": "Cup"}, {"ticker": "BLFS", "rs": 85, "pattern": "Cup"}, {"ticker": "HAE", "rs": 78, "pattern": "Cup"}]}, {"industry": "Health Care Distributors", "rs_line_avg": 58, "count": 4, "top_tickers": [{"ticker": "CAH", "rs": 74, "pattern": "VCP"}, {"ticker": "HSIC", "rs": 64, "pattern": "VCP"}, {"ticker": "MCK", "rs": 42, "pattern": "VCP"}, {"ticker": "COR", "rs": 29, "pattern": "VCP"}]}, {"industry": "Managed Health Care", "rs_line_avg": 57, "count": 6, "top_tickers": [{"ticker": "CNC", "rs": 97, "pattern": "HT Flag"}, {"ticker": "HUM", "rs": 97, "pattern": "HT Flag"}, {"ticker": "MOH", "rs": 89, "pattern": "Cup"}, {"ticker": "UNH", "rs": 86, "pattern": "VCP"}, {"ticker": "ELV", "rs": 79, "pattern": "Cup"}, {"ticker": "HQY", "rs": 46, "pattern": "Cup"}]}, {"industry": "Life Sciences Tools & Services", "rs_line_avg": 57, "count": 13, "top_tickers": [{"ticker": "ILMN", "rs": 93, "pattern": "HT Flag"}, {"ticker": "MEDP", "rs": 84, "pattern": "Cup"}, {"ticker": "CRL", "rs": 80, "pattern": "HT Flag"}, {"ticker": "TECH", "rs": 78, "pattern": "HT Flag"}, {"ticker": "IQV", "rs": 75, "pattern": "Cup"}, {"ticker": "WAT", "rs": 61, "pattern": "VCP"}]}, {"industry": "Regional Banks", "rs_line_avg": 57, "count": 1, "top_tickers": [{"ticker": "HFWA", "rs": 62, "pattern": "Cup"}]}, {"industry": "Health Care Facilities", "rs_line_avg": 56, "count": 11, "top_tickers": [{"ticker": "ACHC", "rs": 96, "pattern": "Cup"}, {"ticker": "ASTH", "rs": 94, "pattern": "Cup"}, {"ticker": "NHC", "rs": 94, "pattern": "Cup"}, {"ticker": "ENSG", "rs": 45, "pattern": "VCP"}, {"ticker": "SEM", "rs": 43, "pattern": "Flat Base"}, {"ticker": "THC", "rs": 42, "pattern": "Cup"}]}, {"industry": "Health Care Technology", "rs_line_avg": 56, "count": 7, "top_tickers": [{"ticker": "OMCL", "rs": 90, "pattern": "Cup"}, {"ticker": "HSTM", "rs": 72, "pattern": "Cup"}, {"ticker": "SOLV", "rs": 52, "pattern": "VCP"}, {"ticker": "CERT", "rs": 23, "pattern": "HT Flag"}, {"ticker": "VEEV", "rs": 22, "pattern": "Cup"}, {"ticker": "WAY", "rs": 5, "pattern": "Cup"}]}], "small_sector": false, "health_grade": "중립", "health_color": "#854F0B"}, {"sector": "Financials", "count": 257, "rs_now_avg": 50, "rs_line_avg": 55, "rs_line_bayes": 55, "sector_health": -0.42, "phase_counts": {"newEntry": 5, "recentUp": 27, "progressing": 65, "stagnant": 101, "transDn": 59, "p4Plus": 1, "total": 257}, "industries": [{"industry": "Transaction & Payment Processing Services", "rs_line_avg": 62, "count": 18, "top_tickers": [{"ticker": "SEZL", "rs": 97, "pattern": "HT Flag"}, {"ticker": "NATL", "rs": 81, "pattern": "Cup"}, {"ticker": "RELY", "rs": 80, "pattern": "Cup"}, {"ticker": "PAYO", "rs": 75, "pattern": "HT Flag"}, {"ticker": "CPAY", "rs": 53, "pattern": "Cup"}, {"ticker": "V", "rs": 49, "pattern": "Cup"}]}, {"industry": "Insurance Brokers", "rs_line_avg": 62, "count": 8, "top_tickers": [{"ticker": "AON", "rs": 40, "pattern": "Cup"}, {"ticker": "AJG", "rs": 27, "pattern": "Cup"}, {"ticker": "WTW", "rs": 26, "pattern": "VCP"}, {"ticker": "GSHD", "rs": 25, "pattern": "HT Flag"}, {"ticker": "MRSH", "rs": 23, "pattern": "Cup"}, {"ticker": "RYAN", "rs": 14, "pattern": "Cup"}]}, {"industry": "Application Software", "rs_line_avg": 61, "count": 1, "top_tickers": [{"ticker": "ALRM", "rs": 41, "pattern": "Cup"}]}, {"industry": "Diversified Financial Services", "rs_line_avg": 59, "count": 1, "top_tickers": [{"ticker": "EQH", "rs": 37, "pattern": "Cup"}]}, {"industry": "Reinsurance", "rs_line_avg": 58, "count": 5, "top_tickers": [{"ticker": "RGA", "rs": 65, "pattern": "Cup"}, {"ticker": "RNR", "rs": 64, "pattern": "Cup"}, {"ticker": "SPNT", "rs": 63, "pattern": "Cup"}, {"ticker": "EG", "rs": 51, "pattern": "Cup"}, {"ticker": "MTG", "rs": 50, "pattern": "VCP"}]}, {"industry": "Consumer Finance", "rs_line_avg": 57, "count": 15, "top_tickers": [{"ticker": "DAVE", "rs": 96, "pattern": "HT Flag"}, {"ticker": "ENVA", "rs": 94, "pattern": "Cup"}, {"ticker": "ECPG", "rs": 92, "pattern": "Cup"}, {"ticker": "EZPW", "rs": 91, "pattern": "Cup"}, {"ticker": "PRG", "rs": 88, "pattern": "HT Flag"}, {"ticker": "BFH", "rs": 81, "pattern": "Cup"}]}, {"industry": "Property & Casualty Insurance", "rs_line_avg": 57, "count": 26, "top_tickers": [{"ticker": "UFCS", "rs": 91, "pattern": "Cup"}, {"ticker": "MCY", "rs": 80, "pattern": "Cup"}, {"ticker": "TRV", "rs": 79, "pattern": "Cup"}, {"ticker": "ALL", "rs": 73, "pattern": "Cup"}, {"ticker": "THG", "rs": 73, "pattern": "Cup"}, {"ticker": "HCI", "rs": 71, "pattern": "Cup"}]}, {"industry": "Life & Health Insurance", "rs_line_avg": 57, "count": 12, "top_tickers": [{"ticker": "GL", "rs": 82, "pattern": "Cup"}, {"ticker": "CNO", "rs": 79, "pattern": "Cup"}, {"ticker": "PFG", "rs": 76, "pattern": "Cup"}, {"ticker": "JXN", "rs": 74, "pattern": "Cup"}, {"ticker": "MET", "rs": 67, "pattern": "Cup"}, {"ticker": "BHF", "rs": 65, "pattern": "Cup"}]}], "small_sector": false, "health_grade": "약세", "health_color": "#A32D2D"}, {"sector": "Consumer Staples", "count": 75, "rs_now_avg": 39, "rs_line_avg": 53, "rs_line_bayes": 53, "sector_health": -1.08, "phase_counts": {"newEntry": 2, "recentUp": 7, "progressing": 7, "stagnant": 34, "transDn": 25, "p4Plus": 0, "total": 75}, "industries": [{"industry": "Household Products", "rs_line_avg": 58, "count": 11, "top_tickers": [{"ticker": "EPC", "rs": 68, "pattern": "HT Flag"}, {"ticker": "REYN", "rs": 68, "pattern": "Cup"}, {"ticker": "IPAR", "rs": 60, "pattern": "Cup"}, {"ticker": "CENT", "rs": 55, "pattern": "Cup"}, {"ticker": "WDFC", "rs": 52, "pattern": "Cup"}, {"ticker": "CENTA", "rs": 50, "pattern": "Cup"}]}, {"industry": "Personal Care Products", "rs_line_avg": 58, "count": 4, "top_tickers": [{"ticker": "EL", "rs": 41, "pattern": "VCP"}, {"ticker": "KVUE", "rs": 34, "pattern": "Cup"}, {"ticker": "PG", "rs": 29, "pattern": "Cup"}, {"ticker": "ELF", "rs": 23, "pattern": "HT Flag"}]}, {"industry": "Agricultural Products & Services", "rs_line_avg": 57, "count": 5, "top_tickers": [{"ticker": "DAR", "rs": 86, "pattern": "Cup"}, {"ticker": "ADM", "rs": 85, "pattern": "Cup"}, {"ticker": "BG", "rs": 76, "pattern": "Cup"}, {"ticker": "INGR", "rs": 11, "pattern": "Cup"}, {"ticker": "VITL", "rs": 6, "pattern": "HT Flag"}]}, {"industry": "Food Distributors", "rs_line_avg": 56, "count": 5, "top_tickers": [{"ticker": "CHEF", "rs": 90, "pattern": "HT Flag"}, {"ticker": "ANDE", "rs": 89, "pattern": "Cup"}, {"ticker": "PFGC", "rs": 61, "pattern": "VCP"}, {"ticker": "USFD", "rs": 46, "pattern": "Cup"}, {"ticker": "SYY", "rs": 38, "pattern": "Cup"}]}, {"industry": "Tobacco", "rs_line_avg": 55, "count": 3, "top_tickers": [{"ticker": "MO", "rs": 70, "pattern": "VCP"}, {"ticker": "PM", "rs": 63, "pattern": "VCP"}, {"ticker": "UVV", "rs": 30, "pattern": "Cup"}]}, {"industry": "Consumer Staples Merchandise Retail", "rs_line_avg": 53, "count": 7, "top_tickers": [{"ticker": "PSMT", "rs": 83, "pattern": "Cup"}, {"ticker": "DLTR", "rs": 72, "pattern": "Cup"}, {"ticker": "TGT", "rs": 69, "pattern": "Cup"}, {"ticker": "DG", "rs": 50, "pattern": "Cup"}, {"ticker": "WMT", "rs": 36, "pattern": "Cup"}, {"ticker": "COST", "rs": 25, "pattern": "Cup"}]}, {"industry": "Brewers", "rs_line_avg": 52, "count": 2, "top_tickers": [{"ticker": "TAP", "rs": 16, "pattern": "Cup"}, {"ticker": "SAM", "rs": 15, "pattern": "Cup"}]}, {"industry": "Packaged Foods & Meats", "rs_line_avg": 51, "count": 21, "top_tickers": [{"ticker": "SJM", "rs": 54, "pattern": "Cup"}, {"ticker": "JBSS", "rs": 49, "pattern": "Cup"}, {"ticker": "KHC", "rs": 40, "pattern": "Cup"}, {"ticker": "HRL", "rs": 37, "pattern": "Cup"}, {"ticker": "LW", "rs": 36, "pattern": "Cup"}, {"ticker": "CALM", "rs": 33, "pattern": "Cup"}]}], "small_sector": false, "health_grade": "약세", "health_color": "#A32D2D"}, {"sector": "Consumer Discretionary", "count": 196, "rs_now_avg": 43, "rs_line_avg": 52, "rs_line_bayes": 52, "sector_health": -0.91, "phase_counts": {"newEntry": 5, "recentUp": 17, "progressing": 19, "stagnant": 93, "transDn": 62, "p4Plus": 1, "total": 196}, "industries": [{"industry": "Homefurnishing Retail", "rs_line_avg": 64, "count": 2, "top_tickers": [{"ticker": "RH", "rs": 69, "pattern": "HT Flag"}, {"ticker": "WSM", "rs": 67, "pattern": "Cup"}]}, {"industry": "Housewares & Specialties", "rs_line_avg": 63, "count": 1, "top_tickers": [{"ticker": "NWL", "rs": 40, "pattern": "HT Flag"}]}, {"industry": "Motorcycle Manufacturers", "rs_line_avg": 62, "count": 1, "top_tickers": [{"ticker": "HOG", "rs": 67, "pattern": "Cup"}]}, {"industry": "Tires & Rubber", "rs_line_avg": 62, "count": 1, "top_tickers": [{"ticker": "GT", "rs": 16, "pattern": "VCP"}]}, {"industry": "Computer & Electronics Retail", "rs_line_avg": 58, "count": 3, "top_tickers": [{"ticker": "BBY", "rs": 79, "pattern": "HT Flag"}, {"ticker": "UPBD", "rs": 29, "pattern": "Cup"}, {"ticker": "GME", "rs": 19, "pattern": "VCP"}]}, {"industry": "Specialized Consumer Services", "rs_line_avg": 57, "count": 7, "top_tickers": [{"ticker": "FTDR", "rs": 74, "pattern": "VCP"}, {"ticker": "HRB", "rs": 42, "pattern": "Cup"}, {"ticker": "MATW", "rs": 37, "pattern": "Cup"}, {"ticker": "SCI", "rs": 24, "pattern": "VCP"}, {"ticker": "DASH", "rs": 18, "pattern": "VCP"}, {"ticker": "ADT", "rs": 17, "pattern": "VCP"}]}, {"industry": "Restaurants", "rs_line_avg": 56, "count": 17, "top_tickers": [{"ticker": "BJRI", "rs": 96, "pattern": "HT Flag"}, {"ticker": "CAKE", "rs": 86, "pattern": "Cup"}, {"ticker": "CBRL", "rs": 86, "pattern": "HT Flag"}, {"ticker": "EAT", "rs": 75, "pattern": "HT Flag"}, {"ticker": "TXRH", "rs": 60, "pattern": "VCP"}, {"ticker": "BROS", "rs": 58, "pattern": "Cup"}]}, {"industry": "Leisure Products", "rs_line_avg": 55, "count": 9, "top_tickers": [{"ticker": "CALY", "rs": 93, "pattern": "Cup"}, {"ticker": "PII", "rs": 85, "pattern": "Cup"}, {"ticker": "YETI", "rs": 85, "pattern": "Cup"}, {"ticker": "GOLF", "rs": 74, "pattern": "Cup"}, {"ticker": "PTON", "rs": 65, "pattern": "Cup"}, {"ticker": "BC", "rs": 61, "pattern": "Cup"}]}], "small_sector": false, "health_grade": "약세", "health_color": "#A32D2D"}, {"sector": "Real Estate", "count": 106, "rs_now_avg": 49, "rs_line_avg": 52, "rs_line_bayes": 52, "sector_health": -0.46, "phase_counts": {"newEntry": 4, "recentUp": 9, "progressing": 27, "stagnant": 41, "transDn": 25, "p4Plus": 0, "total": 106}, "industries": [{"industry": "Hotel & Resort REITs", "rs_line_avg": 57, "count": 9, "top_tickers": [{"ticker": "PEB", "rs": 92, "pattern": "Cup"}, {"ticker": "XHR", "rs": 88, "pattern": "Cup"}, {"ticker": "DRH", "rs": 85, "pattern": "Cup"}, {"ticker": "PK", "rs": 82, "pattern": "Cup"}, {"ticker": "APLE", "rs": 82, "pattern": "Cup"}, {"ticker": "HST", "rs": 79, "pattern": "Cup"}]}, {"industry": "Health Care REITs", "rs_line_avg": 57, "count": 11, "top_tickers": [{"ticker": "WELL", "rs": 81, "pattern": "Cup"}, {"ticker": "AHR", "rs": 79, "pattern": "Cup"}, {"ticker": "DOC", "rs": 77, "pattern": "Cup"}, {"ticker": "VTR", "rs": 77, "pattern": "Cup"}, {"ticker": "HR", "rs": 71, "pattern": "VCP"}, {"ticker": "CTRE", "rs": 70, "pattern": "VCP"}]}, {"industry": "Industrial REITs", "rs_line_avg": 57, "count": 9, "top_tickers": [{"ticker": "BNL", "rs": 76, "pattern": "Cup"}, {"ticker": "IIPR", "rs": 71, "pattern": "VCP"}, {"ticker": "EGP", "rs": 67, "pattern": "Cup"}, {"ticker": "FR", "rs": 66, "pattern": "Cup"}, {"ticker": "TRNO", "rs": 66, "pattern": "Cup"}, {"ticker": "PLD", "rs": 64, "pattern": "Cup"}]}, {"industry": "Diversified REITs", "rs_line_avg": 56, "count": 5, "top_tickers": [{"ticker": "LXP", "rs": 79, "pattern": "Cup"}, {"ticker": "AAT", "rs": 73, "pattern": "Cup"}, {"ticker": "WPC", "rs": 52, "pattern": "Cup"}, {"ticker": "GNL", "rs": 52, "pattern": "Flat Base"}, {"ticker": "EPRT", "rs": 38, "pattern": "Cup"}]}, {"industry": "Office REITs", "rs_line_avg": 56, "count": 11, "top_tickers": [{"ticker": "HIW", "rs": 76, "pattern": "Cup"}, {"ticker": "CDP", "rs": 72, "pattern": "Cup"}, {"ticker": "VNO", "rs": 71, "pattern": "Cup"}, {"ticker": "CUZ", "rs": 69, "pattern": "Cup"}, {"ticker": "KRC", "rs": 64, "pattern": "Cup"}, {"ticker": "DEA", "rs": 48, "pattern": "Cup"}]}, {"industry": "Retail REITs", "rs_line_avg": 55, "count": 18, "top_tickers": [{"ticker": "MAC", "rs": 81, "pattern": "Cup"}, {"ticker": "WSR", "rs": 74, "pattern": "Flat Base"}, {"ticker": "SPG", "rs": 72, "pattern": "Cup"}, {"ticker": "CURB", "rs": 72, "pattern": "Cup"}, {"ticker": "FRT", "rs": 69, "pattern": "Cup"}, {"ticker": "KRG", "rs": 69, "pattern": "Cup"}]}, {"industry": "Other Specialized REITs", "rs_line_avg": 52, "count": 7, "top_tickers": [{"ticker": "OUT", "rs": 86, "pattern": "VCP"}, {"ticker": "LAMR", "rs": 73, "pattern": "VCP"}, {"ticker": "IRM", "rs": 58, "pattern": "VCP"}, {"ticker": "EPR", "rs": 45, "pattern": "Cup"}, {"ticker": "SAFE", "rs": 45, "pattern": "Cup"}, {"ticker": "FCPT", "rs": 34, "pattern": "Cup"}]}, {"industry": "Single-Family Residential REITs", "rs_line_avg": 51, "count": 4, "top_tickers": [{"ticker": "INVH", "rs": 33, "pattern": "VCP"}, {"ticker": "ELS", "rs": 33, "pattern": "Cup"}, {"ticker": "AMH", "rs": 32, "pattern": "VCP"}, {"ticker": "MRP", "rs": 21, "pattern": "VCP"}]}], "small_sector": false, "health_grade": "약세", "health_color": "#A32D2D"}, {"sector": "Industrials", "count": 254, "rs_now_avg": 51, "rs_line_avg": 51, "rs_line_bayes": 51, "sector_health": -0.36, "phase_counts": {"newEntry": 4, "recentUp": 56, "progressing": 25, "stagnant": 114, "transDn": 55, "p4Plus": 3, "total": 254}, "industries": [{"industry": "Human Resource & Employment Services", "rs_line_avg": 71, "count": 10, "top_tickers": [{"ticker": "FA", "rs": 94, "pattern": "HT Flag"}, {"ticker": "MAN", "rs": 92, "pattern": "HT Flag"}, {"ticker": "NSP", "rs": 86, "pattern": "HT Flag"}, {"ticker": "RHI", "rs": 81, "pattern": "HT Flag"}, {"ticker": "KFY", "rs": 53, "pattern": "Cup"}, {"ticker": "ADP", "rs": 45, "pattern": "Cup"}]}, {"industry": "Security & Alarm Services", "rs_line_avg": 66, "count": 1, "top_tickers": [{"ticker": "BCO", "rs": 62, "pattern": "Cup"}]}, {"industry": "Technology Distributors", "rs_line_avg": 63, "count": 1, "top_tickers": [{"ticker": "NSIT", "rs": 72, "pattern": "HT Flag"}]}, {"industry": "Office Services & Supplies", "rs_line_avg": 59, "count": 6, "top_tickers": [{"ticker": "PBI", "rs": 90, "pattern": "Cup"}, {"ticker": "TILE", "rs": 81, "pattern": "Cup"}, {"ticker": "MLKN", "rs": 64, "pattern": "HT Flag"}, {"ticker": "WSC", "rs": 43, "pattern": "VCP"}, {"ticker": "MSA", "rs": 28, "pattern": "Cup"}, {"ticker": "HNI", "rs": 25, "pattern": "Cup"}]}, {"industry": "Marine Transportation", "rs_line_avg": 58, "count": 2, "top_tickers": [{"ticker": "MATX", "rs": 93, "pattern": "Cup"}, {"ticker": "KEX", "rs": 66, "pattern": "Cup"}]}, {"industry": "Rail Transportation", "rs_line_avg": 57, "count": 3, "top_tickers": [{"ticker": "CSX", "rs": 78, "pattern": "Cup"}, {"ticker": "UNP", "rs": 73, "pattern": "Cup"}, {"ticker": "NSC", "rs": 59, "pattern": "Cup"}]}, {"industry": "Environmental & Facilities Services", "rs_line_avg": 56, "count": 9, "top_tickers": [{"ticker": "GEO", "rs": 92, "pattern": "HT Flag"}, {"ticker": "HCSG", "rs": 92, "pattern": "Cup"}, {"ticker": "CLH", "rs": 64, "pattern": "VCP"}, {"ticker": "ABM", "rs": 48, "pattern": "Cup"}, {"ticker": "CWST", "rs": 42, "pattern": "VCP"}, {"ticker": "WM", "rs": 41, "pattern": "Cup"}]}, {"industry": "Air Freight & Logistics", "rs_line_avg": 56, "count": 7, "top_tickers": [{"ticker": "CHRW", "rs": 91, "pattern": "Cup"}, {"ticker": "EXPD", "rs": 85, "pattern": "Cup"}, {"ticker": "HUBG", "rs": 80, "pattern": "Cup"}, {"ticker": "UPS", "rs": 52, "pattern": "VCP"}, {"ticker": "FDX", "rs": 48, "pattern": "Cup"}, {"ticker": "GXO", "rs": 27, "pattern": "VCP"}]}], "small_sector": false, "health_grade": "약세", "health_color": "#A32D2D"}, {"sector": "Energy", "count": 69, "rs_now_avg": 62, "rs_line_avg": 50, "rs_line_bayes": 50, "sector_health": 0.27, "phase_counts": {"newEntry": 0, "recentUp": 17, "progressing": 16, "stagnant": 28, "transDn": 8, "p4Plus": 0, "total": 69}, "industries": [{"industry": "Oil & Gas Refining & Marketing", "rs_line_avg": 68, "count": 9, "top_tickers": [{"ticker": "PBF", "rs": 97, "pattern": "HT Flag"}, {"ticker": "DINO", "rs": 95, "pattern": "Cup"}, {"ticker": "PARR", "rs": 95, "pattern": "Cup"}, {"ticker": "VLO", "rs": 94, "pattern": "Cup"}, {"ticker": "MPC", "rs": 93, "pattern": "Cup"}, {"ticker": "PSX", "rs": 89, "pattern": "Cup"}]}, {"industry": "Oil & Gas Storage & Transportation", "rs_line_avg": 53, "count": 10, "top_tickers": [{"ticker": "INSW", "rs": 92, "pattern": "Cup"}, {"ticker": "TRGP", "rs": 87, "pattern": "Cup"}, {"ticker": "LPG", "rs": 82, "pattern": "Cup"}, {"ticker": "DTM", "rs": 70, "pattern": "VCP"}, {"ticker": "AM", "rs": 62, "pattern": "VCP"}, {"ticker": "KNTK", "rs": 61, "pattern": "Cup"}]}, {"industry": "Integrated Oil & Gas", "rs_line_avg": 53, "count": 2, "top_tickers": [{"ticker": "XOM", "rs": 63, "pattern": "Cup"}, {"ticker": "CVX", "rs": 56, "pattern": "Cup"}]}, {"industry": "Oil & Gas Exploration & Production", "rs_line_avg": 47, "count": 24, "top_tickers": [{"ticker": "APA", "rs": 83, "pattern": "VCP"}, {"ticker": "TALO", "rs": 80, "pattern": "Cup"}, {"ticker": "OVV", "rs": 76, "pattern": "Cup"}, {"ticker": "PR", "rs": 76, "pattern": "Cup"}, {"ticker": "SM", "rs": 74, "pattern": "Cup"}, {"ticker": "MUR", "rs": 71, "pattern": "Cup"}]}, {"industry": "Oil & Gas Equipment & Services", "rs_line_avg": 44, "count": 18, "top_tickers": [{"ticker": "OII", "rs": 91, "pattern": "Cup"}, {"ticker": "FTI", "rs": 90, "pattern": "Cup"}, {"ticker": "KGS", "rs": 88, "pattern": "Cup"}, {"ticker": "LBRT", "rs": 88, "pattern": "Cup"}, {"ticker": "HAL", "rs": 79, "pattern": "Cup"}, {"ticker": "AROC", "rs": 78, "pattern": "Cup"}]}, {"industry": "Coal & Consumable Fuels", "rs_line_avg": 43, "count": 2, "top_tickers": [{"ticker": "BTU", "rs": 85, "pattern": "Cup"}, {"ticker": "CNR", "rs": 39, "pattern": "Cup"}]}, {"industry": "Oil & Gas Drilling", "rs_line_avg": 42, "count": 4, "top_tickers": [{"ticker": "HP", "rs": 90, "pattern": "Cup"}, {"ticker": "PTEN", "rs": 82, "pattern": "Cup"}, {"ticker": "VAL", "rs": 74, "pattern": "HT Flag"}, {"ticker": "NE", "rs": 65, "pattern": "Cup"}]}], "small_sector": false, "health_grade": "중립", "health_color": "#854F0B"}, {"sector": "Utilities", "count": 60, "rs_now_avg": 42, "rs_line_avg": 50, "rs_line_bayes": 50, "sector_health": -0.94, "phase_counts": {"newEntry": 0, "recentUp": 1, "progressing": 6, "stagnant": 44, "transDn": 9, "p4Plus": 0, "total": 60}, "industries": [{"industry": "Water Utilities", "rs_line_avg": 57, "count": 6, "top_tickers": [{"ticker": "HTO", "rs": 63, "pattern": "Cup"}, {"ticker": "AWR", "rs": 58, "pattern": "Cup"}, {"ticker": "CWT", "rs": 53, "pattern": "VCP"}, {"ticker": "MSEX", "rs": 39, "pattern": "Cup"}, {"ticker": "WTRG", "rs": 34, "pattern": "VCP"}, {"ticker": "AWK", "rs": 26, "pattern": "VCP"}]}, {"industry": "Gas Utilities", "rs_line_avg": 51, "count": 9, "top_tickers": [{"ticker": "NJR", "rs": 61, "pattern": "Cup"}, {"ticker": "SWX", "rs": 49, "pattern": "Cup"}, {"ticker": "NWN", "rs": 47, "pattern": "VCP"}, {"ticker": "CPK", "rs": 44, "pattern": "Cup"}, {"ticker": "ATO", "rs": 38, "pattern": "VCP"}, {"ticker": "UGI", "rs": 32, "pattern": "VCP"}]}, {"industry": "Electric Utilities", "rs_line_avg": 50, "count": 22, "top_tickers": [{"ticker": "EIX", "rs": 77, "pattern": "Cup"}, {"ticker": "POR", "rs": 61, "pattern": "VCP"}, {"ticker": "ETR", "rs": 55, "pattern": "VCP"}, {"ticker": "EVRG", "rs": 55, "pattern": "Cup"}, {"ticker": "OTTR", "rs": 52, "pattern": "Cup"}, {"ticker": "ES", "rs": 51, "pattern": "Cup"}]}, {"industry": "Multi-Utilities", "rs_line_avg": 50, "count": 17, "top_tickers": [{"ticker": "D", "rs": 62, "pattern": "Cup"}, {"ticker": "NWE", "rs": 62, "pattern": "Cup"}, {"ticker": "PCG", "rs": 59, "pattern": "Cup"}, {"ticker": "BKH", "rs": 56, "pattern": "Cup"}, {"ticker": "PNW", "rs": 48, "pattern": "VCP"}, {"ticker": "MDU", "rs": 47, "pattern": "Cup"}]}, {"industry": "Independent Power Producers & Energy Traders", "rs_line_avg": 45, "count": 3, "top_tickers": [{"ticker": "TLN", "rs": 47, "pattern": "Cup"}, {"ticker": "AES", "rs": 42, "pattern": "Flat Base"}, {"ticker": "NRG", "rs": 14, "pattern": "VCP"}]}, {"industry": "Renewable Electricity", "rs_line_avg": 42, "count": 3, "top_tickers": [{"ticker": "CWEN-A", "rs": 69, "pattern": "VCP"}, {"ticker": "ORA", "rs": 38, "pattern": "Cup"}, {"ticker": "CWEN", "rs": 22, "pattern": "VCP"}]}], "small_sector": false, "health_grade": "약세", "health_color": "#A32D2D"}, {"sector": "Communication Services", "count": 51, "rs_now_avg": 41, "rs_line_avg": 49, "rs_line_bayes": 49, "sector_health": -1.06, "phase_counts": {"newEntry": 1, "recentUp": 7, "progressing": 4, "stagnant": 16, "transDn": 23, "p4Plus": 0, "total": 51}, "industries": [{"industry": "Interactive Media & Services", "rs_line_avg": 55, "count": 10, "top_tickers": [{"ticker": "GOOGL", "rs": 86, "pattern": "VCP"}, {"ticker": "GOOG", "rs": 86, "pattern": "VCP"}, {"ticker": "QNST", "rs": 74, "pattern": "HT Flag"}, {"ticker": "MTCH", "rs": 57, "pattern": "Cup"}, {"ticker": "PPLI", "rs": 42, "pattern": "VCP"}, {"ticker": "TRIP", "rs": 40, "pattern": "HT Flag"}]}, {"industry": "Publishing", "rs_line_avg": 55, "count": 4, "top_tickers": [{"ticker": "WLY", "rs": 77, "pattern": "Cup"}, {"ticker": "NYT", "rs": 62, "pattern": "Cup"}, {"ticker": "NWSA", "rs": 34, "pattern": "Cup"}, {"ticker": "NWS", "rs": 32, "pattern": "Cup"}]}, {"industry": "nan", "rs_line_avg": 55, "count": 1, "top_tickers": [{"ticker": "PINS", "rs": 12, "pattern": "Cup"}]}, {"industry": "Advertising", "rs_line_avg": 53, "count": 4, "top_tickers": [{"ticker": "ZD", "rs": 87, "pattern": "Cup"}, {"ticker": "OMC", "rs": 50, "pattern": "Cup"}, {"ticker": "DV", "rs": 20, "pattern": "Cup"}, {"ticker": "TTD", "rs": 1, "pattern": "Cup"}]}, {"industry": "Interactive Home Entertainment", "rs_line_avg": 53, "count": 2, "top_tickers": [{"ticker": "EA", "rs": 68, "pattern": "Flat Base"}, {"ticker": "TTWO", "rs": 45, "pattern": "Cup"}]}, {"industry": "Broadcasting", "rs_line_avg": 51, "count": 5, "top_tickers": [{"ticker": "WBD", "rs": 88, "pattern": "Flat Base"}, {"ticker": "SIRI", "rs": 71, "pattern": "Cup"}, {"ticker": "FOXA", "rs": 27, "pattern": "Cup"}, {"ticker": "FOX", "rs": 26, "pattern": "Cup"}, {"ticker": "NXST", "rs": 24, "pattern": "Cup"}]}, {"industry": "Movies & Entertainment", "rs_line_avg": 47, "count": 10, "top_tickers": [{"ticker": "SPHR", "rs": 95, "pattern": "Cup"}, {"ticker": "MSGS", "rs": 89, "pattern": "Cup"}, {"ticker": "ROKU", "rs": 83, "pattern": "VCP"}, {"ticker": "LYV", "rs": 64, "pattern": "VCP"}, {"ticker": "CNK", "rs": 45, "pattern": "Cup"}, {"ticker": "TKO", "rs": 36, "pattern": "Cup"}]}, {"industry": "Integrated Telecommunication Services", "rs_line_avg": 43, "count": 3, "top_tickers": [{"ticker": "VZ", "rs": 31, "pattern": "Cup"}, {"ticker": "TDS", "rs": 14, "pattern": "Cup"}, {"ticker": "T", "rs": 12, "pattern": "Cup"}]}], "small_sector": false, "health_grade": "약세", "health_color": "#A32D2D"}, {"sector": "Information Technology", "count": 189, "rs_now_avg": 59, "rs_line_avg": 47, "rs_line_bayes": 48, "sector_health": 0.08, "phase_counts": {"newEntry": 2, "recentUp": 74, "progressing": 9, "stagnant": 55, "transDn": 49, "p4Plus": 1, "total": 189}, "industries": [{"industry": "Systems Software", "rs_line_avg": 64, "count": 14, "top_tickers": [{"ticker": "PANW", "rs": 98, "pattern": "HT Flag"}, {"ticker": "FTNT", "rs": 97, "pattern": "HT Flag"}, {"ticker": "CRWD", "rs": 96, "pattern": "HT Flag"}, {"ticker": "QLYS", "rs": 95, "pattern": "HT Flag"}, {"ticker": "ATEN", "rs": 93, "pattern": "Cup"}, {"ticker": "TWLO", "rs": 91, "pattern": "HT Flag"}]}, {"industry": "Application Software", "rs_line_avg": 54, "count": 38, "top_tickers": [{"ticker": "DDOG", "rs": 98, "pattern": "HT Flag"}, {"ticker": "OKTA", "rs": 97, "pattern": "HT Flag"}, {"ticker": "YOU", "rs": 87, "pattern": "VCP"}, {"ticker": "AGYS", "rs": 85, "pattern": "HT Flag"}, {"ticker": "RNG", "rs": 78, "pattern": "Cup"}, {"ticker": "ACIW", "rs": 76, "pattern": "Cup"}]}, {"industry": "Technology Distributors", "rs_line_avg": 53, "count": 7, "top_tickers": [{"ticker": "ARW", "rs": 85, "pattern": "Cup"}, {"ticker": "SCSC", "rs": 85, "pattern": "Cup"}, {"ticker": "SNX", "rs": 84, "pattern": "Cup"}, {"ticker": "AVT", "rs": 83, "pattern": "Cup"}, {"ticker": "CNXN", "rs": 75, "pattern": "Cup"}, {"ticker": "PLUS", "rs": 63, "pattern": "Cup"}]}, {"industry": "Electronic Equipment & Instruments", "rs_line_avg": 51, "count": 16, "top_tickers": [{"ticker": "RAL", "rs": 92, "pattern": "HT Flag"}, {"ticker": "CGNX", "rs": 88, "pattern": "Cup"}, {"ticker": "KEYS", "rs": 86, "pattern": "Cup"}, {"ticker": "PI", "rs": 83, "pattern": "Cup"}, {"ticker": "DBD", "rs": 67, "pattern": "VCP"}, {"ticker": "NOVT", "rs": 57, "pattern": "Cup"}]}, {"industry": "Technology Hardware, Storage & Peripherals", "rs_line_avg": 48, "count": 11, "top_tickers": [{"ticker": "SNDK", "rs": 99, "pattern": "HT Flag"}, {"ticker": "STX", "rs": 99, "pattern": "HT Flag"}, {"ticker": "WDC", "rs": 99, "pattern": "HT Flag"}, {"ticker": "DELL", "rs": 98, "pattern": "HT Flag"}, {"ticker": "HPE", "rs": 96, "pattern": "HT Flag"}, {"ticker": "NTAP", "rs": 91, "pattern": "HT Flag"}]}, {"industry": "Internet Services & Infrastructure", "rs_line_avg": 46, "count": 6, "top_tickers": [{"ticker": "DOCN", "rs": 98, "pattern": "HT Flag"}, {"ticker": "AKAM", "rs": 86, "pattern": "HT Flag"}, {"ticker": "CLSK", "rs": 77, "pattern": "HT Flag"}, {"ticker": "VRSN", "rs": 30, "pattern": "Cup"}, {"ticker": "MARA", "rs": 10, "pattern": "Cup"}, {"ticker": "GDDY", "rs": 9, "pattern": "Cup"}]}, {"industry": "Communications Equipment", "rs_line_avg": 45, "count": 14, "top_tickers": [{"ticker": "LITE", "rs": 99, "pattern": "Cup"}, {"ticker": "CIEN", "rs": 98, "pattern": "HT Flag"}, {"ticker": "VSAT", "rs": 98, "pattern": "HT Flag"}, {"ticker": "VIAV", "rs": 97, "pattern": "Cup"}, {"ticker": "EXTR", "rs": 95, "pattern": "HT Flag"}, {"ticker": "NTCT", "rs": 89, "pattern": "Cup"}]}, {"industry": "IT Consulting & Other Services", "rs_line_avg": 44, "count": 12, "top_tickers": [{"ticker": "ADEA", "rs": 83, "pattern": "Cup"}, {"ticker": "TDC", "rs": 79, "pattern": "Cup"}, {"ticker": "VYX", "rs": 13, "pattern": "Cup"}, {"ticker": "IBM", "rs": 9, "pattern": "HT Flag"}, {"ticker": "GDYN", "rs": 7, "pattern": "Cup"}, {"ticker": "CTSH", "rs": 5, "pattern": "Cup"}]}], "small_sector": false, "health_grade": "중립", "health_color": "#854F0B"}, {"sector": "Materials", "count": 78, "rs_now_avg": 42, "rs_line_avg": 46, "rs_line_bayes": 47, "sector_health": -0.93, "phase_counts": {"newEntry": 1, "recentUp": 5, "progressing": 4, "stagnant": 54, "transDn": 14, "p4Plus": 0, "total": 78}, "industries": [{"industry": "Metal, Glass & Plastic Containers", "rs_line_avg": 57, "count": 5, "top_tickers": [{"ticker": "GEF", "rs": 54, "pattern": "Cup"}, {"ticker": "BALL", "rs": 37, "pattern": "VCP"}, {"ticker": "SLGN", "rs": 27, "pattern": "Cup"}, {"ticker": "ATR", "rs": 19, "pattern": "Cup"}, {"ticker": "OI", "rs": 6, "pattern": "Cup"}]}, {"industry": "Fertilizers & Agricultural Chemicals", "rs_line_avg": 53, "count": 5, "top_tickers": [{"ticker": "CF", "rs": 68, "pattern": "Cup"}, {"ticker": "CTVA", "rs": 58, "pattern": "Cup"}, {"ticker": "SMG", "rs": 41, "pattern": "Cup"}, {"ticker": "MOS", "rs": 7, "pattern": "Cup"}, {"ticker": "FMC", "rs": 1, "pattern": "Cup"}]}, {"industry": "Paper & Plastic Packaging Products & Materials", "rs_line_avg": 53, "count": 8, "top_tickers": [{"ticker": "PKG", "rs": 51, "pattern": "Cup"}, {"ticker": "CCK", "rs": 49, "pattern": "Cup"}, {"ticker": "SON", "rs": 47, "pattern": "Cup"}, {"ticker": "SW", "rs": 28, "pattern": "Cup"}, {"ticker": "AMCR", "rs": 27, "pattern": "Cup"}, {"ticker": "AVY", "rs": 19, "pattern": "Cup"}]}, {"industry": "Commodity Chemicals", "rs_line_avg": 50, "count": 3, "top_tickers": [{"ticker": "KOP", "rs": 87, "pattern": "Cup"}, {"ticker": "DOW", "rs": 31, "pattern": "Cup"}, {"ticker": "HWKN", "rs": 18, "pattern": "Cup"}]}, {"industry": "Industrial Gases", "rs_line_avg": 50, "count": 2, "top_tickers": [{"ticker": "LIN", "rs": 42, "pattern": "Cup"}, {"ticker": "APD", "rs": 32, "pattern": "Cup"}]}, {"industry": "Diversified Chemicals", "rs_line_avg": 47, "count": 4, "top_tickers": [{"ticker": "ASH", "rs": 75, "pattern": "Cup"}, {"ticker": "CBT", "rs": 65, "pattern": "VCP"}, {"ticker": "CC", "rs": 40, "pattern": "HT Flag"}, {"ticker": "OLN", "rs": 26, "pattern": "Cup"}]}, {"industry": "Agricultural & Farm Machinery", "rs_line_avg": 47, "count": 1, "top_tickers": [{"ticker": "LNN", "rs": 20, "pattern": "Cup"}]}, {"industry": "Forest Products", "rs_line_avg": 47, "count": 1, "top_tickers": [{"ticker": "LPX", "rs": 17, "pattern": "Cup"}]}], "small_sector": false, "health_grade": "약세", "health_color": "#A32D2D"}]}